toddleocr/__init__.py
toddleocr/__main__.py
toddleocr/_appdir.py
toddleocr/config.py
toddleocr/engine.py
toddleocr/datasets/__init__.py
toddleocr/datasets/cocoseg.py
toddleocr/datasets/collate_fn.py
toddleocr/datasets/lmdb.py
toddleocr/datasets/pgnet.py
toddleocr/datasets/pubtab.py
toddleocr/datasets/simple.py
toddleocr/datasets/table.py
toddleocr/loss/__init__.py
toddleocr/loss/ace.py
toddleocr/loss/aster.py
toddleocr/loss/att.py
toddleocr/loss/basic.py
toddleocr/loss/can.py
toddleocr/loss/ce.py
toddleocr/loss/center.py
toddleocr/loss/cls.py
toddleocr/loss/compose.py
toddleocr/loss/ct.py
toddleocr/loss/ctc.py
toddleocr/loss/db.py
toddleocr/loss/distillation.py
toddleocr/loss/drrg.py
toddleocr/loss/east.py
toddleocr/loss/fce.py
toddleocr/loss/pg.py
toddleocr/loss/pren.py
toddleocr/loss/pse.py
toddleocr/loss/rfl.py
toddleocr/loss/sar.py
toddleocr/loss/sast.py
toddleocr/loss/sdmgr.py
toddleocr/loss/spin.py
toddleocr/loss/srn.py
toddleocr/loss/stroke_focus.py
toddleocr/loss/table_att.py
toddleocr/loss/table_master.py
toddleocr/loss/text_focus.py
toddleocr/loss/vl.py
toddleocr/loss/vqa_token_layoutlm.py
toddleocr/metrics/__init__.py
toddleocr/metrics/_det_eval.py
toddleocr/metrics/_eval_det_iou.py
toddleocr/metrics/cls.py
toddleocr/metrics/ct.py
toddleocr/metrics/det.py
toddleocr/metrics/distillation.py
toddleocr/metrics/e2e.py
toddleocr/metrics/kie.py
toddleocr/metrics/rec.py
toddleocr/metrics/sr.py
toddleocr/metrics/table.py
toddleocr/metrics/vqa.py
toddleocr/models/__init__.py
toddleocr/modules/__init__.py
toddleocr/modules/architectures/__init__.py
toddleocr/modules/architectures/base_model.py
toddleocr/modules/architectures/distillation_model.py
toddleocr/modules/backbones/__init__.py
toddleocr/modules/backbones/det_pp_lcnet.py
toddleocr/modules/backbones/kie_unet_sdmgr.py
toddleocr/modules/backbones/rec_densenet.py
toddleocr/modules/backbones/rec_efficientb3_pren.py
toddleocr/modules/backbones/rec_micronet.py
toddleocr/modules/backbones/rec_mv1_enhance.py
toddleocr-1.2.8.dist-info/LICENSE
toddleocr-1.2.8.dist-info/METADATA
toddleocr-1.2.8.dist-info/WHEEL
toddleocr-1.2.8.dist-info/entry_points.txt
toddleocr-1.2.8.dist-info/top_level.txt
toddleocr-1.2.8.dist-info/RECORD
