Metadata-Version: 2.1
Name: toddleocr
Version: 1.2.8
Summary: Awesome OCR toolkits based on Torch （8.6M ultra-lightweight pre-trained model, support training and deployment among server, mobile, embedded and IoT devices
Home-page: https://github.com/arry-lee/ToddleOCR
Download-URL: https://github.com/arry-lee/ToddleOCR.git
License: Apache License 2.0
Keywords: ocr textdetection textrecognition toddleocr crnn east star-net rosetta ocrlite db chineseocr chinesetextdetection chinesetextrecognition
Classifier: Intended Audience :: Developers
Classifier: Operating System :: OS Independent
Classifier: Natural Language :: Chinese (Simplified)
Classifier: Programming Language :: Python :: 3.7
Classifier: Programming Language :: Python :: 3.8
Classifier: Programming Language :: Python :: 3.9
Classifier: Programming Language :: Python :: 3.10
Classifier: Programming Language :: Python :: 3.11
Classifier: Topic :: Utilities
Requires-Python: >=3.8
License-File: LICENSE
Requires-Dist: torch ~=2.0.1
Requires-Dist: torchvision ~=0.15.2
Requires-Dist: numpy ~=1.25.1
Requires-Dist: opencv-python ~=4.8.0.74
Requires-Dist: visualdl ~=2.5.3
Requires-Dist: scikit-image ~=0.21.0
Requires-Dist: Pillow ~=10.0.0
Requires-Dist: scipy ~=1.11.1
Requires-Dist: shapely ~=2.0.1
Requires-Dist: requests ~=2.31.0
Requires-Dist: tqdm ~=4.65.0
Requires-Dist: loguru ~=0.7.0
Requires-Dist: rapidfuzz ~=3.2.0
Requires-Dist: paddlenlp ~=2.6.0
Requires-Dist: lmdb ~=1.4.1
Requires-Dist: six ~=1.16.0
Requires-Dist: pyclipper ~=1.3.0.post4
Requires-Dist: imgaug ~=0.4.0
Requires-Dist: PyYAML ~=6.0.1
Requires-Dist: matplotlib ~=3.7.2
Requires-Dist: setuptools ~=65.5.1
